leap.soledad.common-0.9.6.post2-py2.7-nspkg.pth
leap/soledad/common/__init__.py
leap/soledad/common/_version.py
leap/soledad/common/backend.py
leap/soledad/common/command.py
leap/soledad/common/crypto.py
leap/soledad/common/document.py
leap/soledad/common/errors.py
leap/soledad/common/log.py
leap/soledad/common/couch/__init__.py
leap/soledad/common/couch/state.py
leap/soledad/common/couch/support.py
leap/soledad/common/l2db/__init__.py
leap/soledad/common/l2db/errors.py
leap/soledad/common/l2db/query_parser.py
leap/soledad/common/l2db/sync.py
leap/soledad/common/l2db/vectorclock.py
leap/soledad/common/l2db/backends/__init__.py
leap/soledad/common/l2db/backends/inmemory.py
leap/soledad/common/l2db/remote/__init__.py
leap/soledad/common/l2db/remote/http_app.py
leap/soledad/common/l2db/remote/http_client.py
leap/soledad/common/l2db/remote/http_database.py
leap/soledad/common/l2db/remote/http_errors.py
leap/soledad/common/l2db/remote/http_target.py
leap/soledad/common/l2db/remote/server_state.py
leap/soledad/common/l2db/remote/ssl_match_hostname.py
leap/soledad/common/l2db/remote/utils.py
leap.soledad.common-0.9.6.post2.dist-info/DESCRIPTION.rst
leap.soledad.common-0.9.6.post2.dist-info/METADATA
leap.soledad.common-0.9.6.post2.dist-info/RECORD
leap.soledad.common-0.9.6.post2.dist-info/WHEEL
leap.soledad.common-0.9.6.post2.dist-info/metadata.json
leap.soledad.common-0.9.6.post2.dist-info/namespace_packages.txt
leap.soledad.common-0.9.6.post2.dist-info/pbr.json
leap.soledad.common-0.9.6.post2.dist-info/top_level.txt
